./README.md
./__init__.py
./pyproject.toml
./sts.py
./stt.py
./tts.py
./vad.py
./tests/test_base_consistency.py
./tests/test_sts_base.py
getstream_plugins_common-0.1.1.dist-info/METADATA
getstream_plugins_common-0.1.1.dist-info/WHEEL
getstream_plugins_common-0.1.1.dist-info/RECORD
