Metadata-Version: 2.4
Name: getstream-plugins-common
Version: 0.1.1
Summary: Common plugin for GetStream
License-Expression: MIT
Requires-Python: >=3.10
Requires-Dist: getstream[webrtc]
